{"word":"PROFILINGS","length":10,"playability":3.0,"playability_order":3017,"min_playability_order":1835,"max_playability_order":3031,"combinations0":1990656,"probability_order0":17455,"min_probability_order0":17106,"max_probability_order0":17461,"combinations1":12109824,"probability_order1":17492,"min_probability_order1":17443,"max_probability_order1":17495,"combinations2":17729280,"probability_order2":17526,"min_probability_order2":17516,"max_probability_order2":17529,"alphagram":"FGIILNOPRS","num_anagrams":1,"num_unique_letters":9,"num_vowels":3,"point_value":16,"front_hooks":null,"back_hooks":null,"is_front_hook":0,"is_back_hook":1,"lexicon_symbols":null,"definition":"PROFILING, the process of compiling a profile of a person's physical (e.g. DNA) or psychological characteristics [n]"}