{"word":"CORPORAS","length":8,"playability":50.1333,"playability_order":19341,"min_playability_order":19341,"max_playability_order":19341,"combinations0":60480,"probability_order0":28308,"min_probability_order0":28294,"max_probability_order0":28348,"combinations1":308064,"probability_order1":29329,"min_probability_order1":29323,"max_probability_order1":29341,"combinations2":416256,"probability_order2":29601,"min_probability_order2":29595,"max_probability_order2":29614,"alphagram":"ACOOPRRS","num_anagrams":1,"num_unique_letters":6,"num_vowels":3,"point_value":12,"front_hooks":null,"back_hooks":null,"is_front_hook":0,"is_back_hook":1,"lexicon_symbols":null,"definition":"(obsolete) a white cloth on which Communion bread and wine are placed, also CORPORAL, CORPORALE [n -ES]"}