{"word":"CULOTTES","length":8,"playability":58.8552,"playability_order":16847,"min_playability_order":16847,"max_playability_order":16847,"combinations0":184320,"probability_order0":16457,"min_probability_order0":16449,"max_probability_order0":16470,"combinations1":869376,"probability_order1":16843,"min_probability_order1":16835,"max_probability_order1":16855,"combinations2":1142784,"probability_order2":17134,"min_probability_order2":17126,"max_probability_order2":17146,"alphagram":"CELOSTTU","num_anagrams":1,"num_unique_letters":7,"num_vowels":3,"point_value":10,"front_hooks":null,"back_hooks":null,"is_front_hook":0,"is_back_hook":1,"lexicon_symbols":null,"definition":"CULOTTE, (French) a divided skirt [n]"}