{"word":"SLEEKS","length":6,"playability":6.53333,"playability_order":22040,"min_playability_order":22040,"max_playability_order":22040,"combinations0":1584,"probability_order0":19440,"min_probability_order0":19399,"max_probability_order0":19457,"combinations1":8232,"probability_order1":19469,"min_probability_order1":19464,"max_probability_order1":19470,"combinations2":10788,"probability_order2":19486,"min_probability_order2":19481,"max_probability_order2":19487,"alphagram":"EEKLSS","num_anagrams":1,"num_unique_letters":4,"num_vowels":2,"point_value":10,"front_hooks":null,"back_hooks":null,"is_front_hook":1,"is_back_hook":1,"lexicon_symbols":null,"definition":"SLEEK, to make smooth, also SLEEKEN [v]"}