{"word":"SUTTAS","length":6,"playability":2.2605,"playability_order":22575,"min_playability_order":22575,"max_playability_order":22575,"combinations0":3240,"probability_order0":16580,"min_probability_order0":16545,"max_probability_order0":16605,"combinations1":12492,"probability_order1":17592,"min_probability_order1":17589,"max_probability_order1":17593,"combinations2":15450,"probability_order2":17859,"min_probability_order2":17856,"max_probability_order2":17860,"alphagram":"ASSTTU","num_anagrams":2,"num_unique_letters":4,"num_vowels":2,"point_value":6,"front_hooks":null,"back_hooks":null,"is_front_hook":0,"is_back_hook":1,"lexicon_symbols":null,"definition":"SUTTA, (Pali) a precept; an aphorism; a brief rule, also SUTRA [n]"}