{"word":"CONNECTERS","length":10,"playability":1.0,"playability_order":10930,"min_playability_order":6272,"max_playability_order":13369,"combinations0":1140480,"probability_order0":21872,"min_probability_order0":21757,"max_probability_order0":21973,"combinations1":8645184,"probability_order1":20676,"min_probability_order1":20673,"max_probability_order1":20678,"combinations2":13584600,"probability_order2":20286,"min_probability_order2":20283,"max_probability_order2":20288,"alphagram":"CCEENNORST","num_anagrams":4,"num_unique_letters":7,"num_vowels":3,"point_value":14,"front_hooks":null,"back_hooks":null,"is_front_hook":0,"is_back_hook":1,"lexicon_symbols":null,"definition":"CONNECTER, something that connects, also CONNECTOR [n]"}