{"word":"PENSIONNATS","length":11,"playability":0.0,"playability_order":17897,"min_playability_order":2783,"max_playability_order":29010,"combinations0":11197440,"probability_order0":10145,"min_probability_order0":9963,"max_probability_order0":10215,"combinations1":67495680,"probability_order1":10573,"min_probability_order1":10573,"max_probability_order1":10575,"combinations2":100645632,"probability_order2":10687,"min_probability_order2":10687,"max_probability_order2":10688,"alphagram":"AEINNNOPSST","num_anagrams":1,"num_unique_letters":8,"num_vowels":4,"point_value":13,"front_hooks":null,"back_hooks":null,"is_front_hook":0,"is_back_hook":1,"lexicon_symbols":null,"definition":"PENSIONNAT, (French) a boarding-school [n]"}