{"word":"THICKEST","length":8,"playability":10.9583,"playability_order":36231,"min_playability_order":36230,"max_playability_order":36231,"combinations0":25920,"probability_order0":34394,"min_probability_order0":34308,"max_probability_order0":34478,"combinations1":173376,"probability_order1":33890,"min_probability_order1":33885,"max_probability_order1":33894,"combinations2":257388,"probability_order2":33725,"min_probability_order2":33720,"max_probability_order2":33729,"alphagram":"CEHIKSTT","num_anagrams":3,"num_unique_letters":7,"num_vowels":2,"point_value":17,"front_hooks":null,"back_hooks":null,"is_front_hook":1,"is_back_hook":0,"lexicon_symbols":null,"definition":"THICK, having a great distance in measurement from surface to surface in the lesser dimension [adj]"}