{"word":"FLUFF","length":5,"playability":1.0,"playability_order":12857,"min_playability_order":12847,"max_playability_order":12860,"combinations0":0,"probability_order0":12873,"min_probability_order0":12787,"max_probability_order0":12915,"combinations1":32,"probability_order1":12900,"min_probability_order1":12898,"max_probability_order1":12907,"combinations2":72,"probability_order2":12899,"min_probability_order2":12899,"max_probability_order2":12901,"alphagram":"FFFLU","num_anagrams":1,"num_unique_letters":3,"num_vowels":1,"point_value":14,"front_hooks":null,"back_hooks":"sy","is_front_hook":1,"is_back_hook":0,"lexicon_symbols":null,"definition":"a soft down from cotton, etc. [n -S] / to make fluffy [v -ED, -ING, -S]"}