{"word":"MAZEDNESSES","length":11,"playability":0.0,"playability_order":13719,"min_playability_order":2783,"max_playability_order":29010,"combinations0":380160,"probability_order0":25981,"min_probability_order0":25975,"max_probability_order0":26013,"combinations1":3290496,"probability_order1":26168,"min_probability_order1":26167,"max_probability_order1":26172,"combinations2":5774528,"probability_order2":26258,"min_probability_order2":26257,"max_probability_order2":26260,"alphagram":"ADEEEMNSSSZ","num_anagrams":1,"num_unique_letters":7,"num_vowels":4,"point_value":23,"front_hooks":"a","back_hooks":null,"is_front_hook":0,"is_back_hook":0,"lexicon_symbols":null,"definition":"MAZEDNESS, the state of being mazed [n]"}