{"word":"UNDERCARRIAGES","length":14,"playability":0.0,"playability_order":1149,"min_playability_order":22,"max_playability_order":9396,"combinations0":985374720,"probability_order0":1516,"min_probability_order0":1514,"max_probability_order0":1540,"combinations1":6982225920,"probability_order1":1619,"min_probability_order1":1619,"max_probability_order1":1619,"combinations2":11267859456,"probability_order2":1654,"min_probability_order2":1654,"max_probability_order2":1654,"alphagram":"AACDEEGINRRRSU","num_anagrams":1,"num_unique_letters":10,"num_vowels":6,"point_value":18,"front_hooks":null,"back_hooks":null,"is_front_hook":0,"is_back_hook":1,"lexicon_symbols":null,"definition":"UNDERCARRIAGE, a supporting framework or underside (as of an automobile) [n]"}