{"word":"DIGLADIATED","length":11,"playability":0.5,"playability_order":2744,"min_playability_order":2744,"max_playability_order":2766,"combinations0":4478976,"probability_order0":15930,"min_probability_order0":15854,"max_probability_order0":16176,"combinations1":29859840,"probability_order1":16396,"min_probability_order1":16396,"max_probability_order1":16399,"combinations2":46780416,"probability_order2":16495,"min_probability_order2":16491,"max_probability_order2":16497,"alphagram":"AADDDEGIILT","num_anagrams":1,"num_unique_letters":7,"num_vowels":5,"point_value":15,"front_hooks":null,"back_hooks":null,"is_front_hook":0,"is_back_hook":1,"lexicon_symbols":null,"definition":"DIGLADIATE, (obsolete) to fight with swords; to fence [v]"}