{"word":"APPROPINQUING","length":13,"playability":0.0,"playability_order":9845,"min_playability_order":125,"max_playability_order":14342,"combinations0":0,"probability_order0":14155,"min_probability_order0":13928,"max_probability_order0":14342,"combinations1":5598720,"probability_order1":13806,"min_probability_order1":13805,"max_probability_order1":13806,"combinations2":18576864,"probability_order2":13648,"min_probability_order2":13648,"max_probability_order2":13648,"alphagram":"AGIINNOPPPQRU","num_anagrams":1,"num_unique_letters":9,"num_vowels":5,"point_value":29,"front_hooks":null,"back_hooks":null,"is_front_hook":0,"is_back_hook":0,"lexicon_symbols":null,"definition":"APPROPINQUE, (archaic) to approach, also APPROPINQUATE [v]"}