{"word":"DEMYTHOLOGISED","length":14,"playability":0.0,"playability_order":8368,"min_playability_order":22,"max_playability_order":9396,"combinations0":229920768,"probability_order0":3910,"min_probability_order0":3895,"max_probability_order0":3915,"combinations1":1952169984,"probability_order1":3899,"min_probability_order1":3898,"max_probability_order1":3900,"combinations2":3432519936,"probability_order2":3892,"min_probability_order2":3891,"max_probability_order2":3893,"alphagram":"DDEEGHILMOOSTY","num_anagrams":1,"num_unique_letters":11,"num_vowels":5,"point_value":25,"front_hooks":null,"back_hooks":null,"is_front_hook":0,"is_back_hook":1,"lexicon_symbols":null,"definition":"DEMYTHOLOGISE, to remove mythology from in order to arrive at the basic meaning, also DEMYTHOLOGIZE [v]"}