{"word":"DIALLEL","length":7,"playability":27.5,"playability_order":26375,"min_playability_order":26371,"max_playability_order":26386,"combinations0":15552,"probability_order0":23011,"min_probability_order0":22730,"max_probability_order0":23555,"combinations1":79488,"probability_order1":23162,"min_probability_order1":23159,"max_probability_order1":23168,"combinations2":109668,"probability_order2":22985,"min_probability_order2":22983,"max_probability_order2":22988,"alphagram":"ADEILLL","num_anagrams":1,"num_unique_letters":5,"num_vowels":3,"point_value":8,"front_hooks":null,"back_hooks":"s","is_front_hook":0,"is_back_hook":0,"lexicon_symbols":null,"definition":"a scheme of crossbreeding within a select group of parents, designed to produce various hybrids with different genetic properties [n -S]"}