{"word":"MARIACHI","length":8,"playability":26.0873,"playability_order":28595,"min_playability_order":28595,"max_playability_order":28595,"combinations0":62208,"probability_order0":27293,"min_probability_order0":27231,"max_probability_order0":28291,"combinations1":331776,"probability_order1":28403,"min_probability_order1":28387,"max_probability_order1":28486,"combinations2":453168,"probability_order2":28855,"min_probability_order2":28855,"max_probability_order2":28855,"alphagram":"AACHIIMR","num_anagrams":1,"num_unique_letters":6,"num_vowels":4,"point_value":15,"front_hooks":null,"back_hooks":"s","is_front_hook":0,"is_back_hook":0,"lexicon_symbols":null,"definition":"(Spanish) a Mexican musical band [n -S]"}