{"word":"HAULING","length":7,"playability":67.7222,"playability_order":15988,"min_playability_order":15988,"max_playability_order":15988,"combinations0":46656,"probability_order0":13130,"min_probability_order0":12711,"max_probability_order0":13373,"combinations1":207360,"probability_order1":12963,"min_probability_order1":12876,"max_probability_order1":12999,"combinations2":263988,"probability_order2":13036,"min_probability_order2":13006,"max_probability_order2":13063,"alphagram":"AGHILNU","num_anagrams":2,"num_unique_letters":7,"num_vowels":3,"point_value":11,"front_hooks":"s","back_hooks":"s","is_front_hook":0,"is_back_hook":0,"lexicon_symbols":null,"definition":"the act of dragging [n -S]"}