{"word":"YEA","length":3,"playability":13864.6,"playability_order":147,"min_playability_order":147,"max_playability_order":147,"combinations0":216,"probability_order0":142,"min_probability_order0":122,"max_probability_order0":191,"combinations1":516,"probability_order1":132,"min_probability_order1":118,"max_probability_order1":137,"combinations2":539,"probability_order2":132,"min_probability_order2":118,"max_probability_order2":137,"alphagram":"AEY","num_anagrams":3,"num_unique_letters":3,"num_vowels":2,"point_value":6,"front_hooks":null,"back_hooks":"dhnrs","is_front_hook":1,"is_back_hook":1,"lexicon_symbols":null,"definition":"an affirmative vote, also YAY [n -S]"}