{"word":"NURTURES","length":8,"playability":82.2814,"playability_order":11562,"min_playability_order":11562,"max_playability_order":11562,"combinations0":155520,"probability_order0":18468,"min_probability_order0":18091,"max_probability_order0":18513,"combinations1":694656,"probability_order1":19695,"min_probability_order1":19682,"max_probability_order1":19702,"combinations2":907848,"probability_order2":20161,"min_probability_order2":20158,"max_probability_order2":20163,"alphagram":"ENRRSTUU","num_anagrams":1,"num_unique_letters":6,"num_vowels":3,"point_value":8,"front_hooks":null,"back_hooks":null,"is_front_hook":0,"is_back_hook":1,"lexicon_symbols":null,"definition":"NURTURE, to nourish [v]"}