{"word":"MISJUDGED","length":9,"playability":9.0,"playability_order":11739,"min_playability_order":11335,"max_playability_order":11902,"combinations0":62208,"probability_order0":37123,"min_probability_order0":36752,"max_probability_order0":37240,"combinations1":459648,"probability_order1":36928,"min_probability_order1":36927,"max_probability_order1":36929,"combinations2":726768,"probability_order2":36918,"min_probability_order2":36918,"max_probability_order2":36919,"alphagram":"DDEGIJMSU","num_anagrams":1,"num_unique_letters":8,"num_vowels":3,"point_value":21,"front_hooks":null,"back_hooks":null,"is_front_hook":0,"is_back_hook":1,"lexicon_symbols":null,"definition":"MISJUDGE, to judge wrongly [v]"}