{"word":"REDEPLOYS","length":9,"playability":10.75,"playability_order":9811,"min_playability_order":9802,"max_playability_order":9813,"combinations0":811008,"probability_order0":15333,"min_probability_order0":15310,"max_probability_order0":15339,"combinations1":4417536,"probability_order1":15236,"min_probability_order1":15213,"max_probability_order1":15242,"combinations2":6124800,"probability_order2":15219,"min_probability_order2":15196,"max_probability_order2":15225,"alphagram":"DEELOPRSY","num_anagrams":3,"num_unique_letters":8,"num_vowels":3,"point_value":15,"front_hooks":null,"back_hooks":null,"is_front_hook":0,"is_back_hook":1,"lexicon_symbols":null,"definition":"REDEPLOY, to deploy again [v]"}