{"word":"REGEARING","length":9,"playability":3.33333,"playability_order":22689,"min_playability_order":22631,"max_playability_order":22785,"combinations0":1443420,"probability_order0":9564,"min_probability_order0":9562,"max_probability_order0":9564,"combinations1":7132536,"probability_order1":9935,"min_probability_order1":9934,"max_probability_order1":9935,"combinations2":9635760,"probability_order2":9901,"min_probability_order2":9900,"max_probability_order2":9901,"alphagram":"AEEGGINRR","num_anagrams":2,"num_unique_letters":6,"num_vowels":4,"point_value":11,"front_hooks":null,"back_hooks":null,"is_front_hook":0,"is_back_hook":0,"lexicon_symbols":null,"definition":"REGEAR, to equip again [v]"}