{"word":"SHOOK","length":5,"playability":169.333,"playability_order":7563,"min_playability_order":7563,"max_playability_order":7563,"combinations0":224,"probability_order0":11568,"min_probability_order0":11542,"max_probability_order0":11583,"combinations1":1136,"probability_order1":11646,"min_probability_order1":11633,"max_probability_order1":11658,"combinations2":1452,"probability_order2":11682,"min_probability_order2":11668,"max_probability_order2":11694,"alphagram":"HKOOS","num_anagrams":2,"num_unique_letters":4,"num_vowels":2,"point_value":12,"front_hooks":null,"back_hooks":"s","is_front_hook":1,"is_back_hook":1,"lexicon_symbols":null,"definition":"a bundle of sheaves [n -S]"}