{"word":"HALOPHOBES","length":10,"playability":0.0,"playability_order":18836,"min_playability_order":13977,"max_playability_order":37196,"combinations0":193536,"probability_order0":32080,"min_probability_order0":32063,"max_probability_order0":32180,"combinations1":1734144,"probability_order1":31753,"min_probability_order1":31753,"max_probability_order1":31755,"combinations2":3010240,"probability_order2":31517,"min_probability_order2":31517,"max_probability_order2":31519,"alphagram":"ABEHHLOOPS","num_anagrams":1,"num_unique_letters":8,"num_vowels":4,"point_value":20,"front_hooks":null,"back_hooks":null,"is_front_hook":0,"is_back_hook":1,"lexicon_symbols":null,"definition":"HALOPHOBE, a plant that cannot survive in salty soil [n]"}