{"word":"AWEE","length":4,"playability":11277.7,"playability_order":11,"min_playability_order":11,"max_playability_order":11,"combinations0":1188,"probability_order0":683,"min_probability_order0":682,"max_probability_order0":687,"combinations1":3072,"probability_order1":725,"min_probability_order1":724,"max_probability_order1":725,"combinations2":3288,"probability_order2":725,"min_probability_order2":724,"max_probability_order2":725,"alphagram":"AEEW","num_anagrams":1,"num_unique_letters":3,"num_vowels":3,"point_value":7,"front_hooks":null,"back_hooks":"l","is_front_hook":1,"is_back_hook":1,"lexicon_symbols":null,"definition":"awhile [adv]"}