{"word":"NAIRUS","length":6,"playability":114.573,"playability_order":8494,"min_playability_order":8494,"max_playability_order":8494,"combinations0":46656,"probability_order0":1255,"min_probability_order0":983,"max_probability_order0":1305,"combinations1":145152,"probability_order1":1266,"min_probability_order1":1250,"max_probability_order1":1268,"combinations2":166356,"probability_order2":1429,"min_probability_order2":1413,"max_probability_order2":1431,"alphagram":"AINRSU","num_anagrams":1,"num_unique_letters":6,"num_vowels":3,"point_value":6,"front_hooks":null,"back_hooks":null,"is_front_hook":0,"is_back_hook":1,"lexicon_symbols":null,"definition":"NAIRU, an acronym for Non-Accelerating Inflation Rate of Unemployment [n]"}