{"word":"ETRANGERE","length":9,"playability":73.1667,"playability_order":187,"min_playability_order":187,"max_playability_order":187,"combinations0":3207600,"probability_order0":3377,"min_probability_order0":3377,"max_probability_order0":3384,"combinations1":12687840,"probability_order1":4492,"min_probability_order1":4492,"max_probability_order1":4493,"combinations2":15891012,"probability_order2":4937,"min_probability_order2":4937,"max_probability_order2":4938,"alphagram":"AEEEGNRRT","num_anagrams":1,"num_unique_letters":6,"num_vowels":4,"point_value":10,"front_hooks":null,"back_hooks":"s","is_front_hook":0,"is_back_hook":1,"lexicon_symbols":null,"definition":"(French) a (female) foreigner [n -S]"}