{"word":"VOCAB","length":5,"playability":1750.42,"playability_order":370,"min_playability_order":370,"max_playability_order":370,"combinations0":576,"probability_order0":9641,"min_probability_order0":9586,"max_probability_order0":10079,"combinations1":2576,"probability_order1":9640,"min_probability_order1":9639,"max_probability_order1":9657,"combinations2":3220,"probability_order2":9647,"min_probability_order2":9646,"max_probability_order2":9664,"alphagram":"ABCOV","num_anagrams":1,"num_unique_letters":5,"num_vowels":2,"point_value":12,"front_hooks":null,"back_hooks":"s","is_front_hook":0,"is_back_hook":0,"lexicon_symbols":null,"definition":"(short for) vocabulary [n -S]"}