{"word":"OBSEQUY","length":7,"playability":50.0,"playability_order":20032,"min_playability_order":20030,"max_playability_order":20037,"combinations0":6144,"probability_order0":28708,"min_probability_order0":28689,"max_probability_order0":28768,"combinations1":39424,"probability_order1":28153,"min_probability_order1":28147,"max_probability_order1":28170,"combinations2":56896,"probability_order2":27977,"min_probability_order2":27972,"max_probability_order2":27988,"alphagram":"BEOQSUY","num_anagrams":1,"num_unique_letters":7,"num_vowels":3,"point_value":21,"front_hooks":null,"back_hooks":null,"is_front_hook":0,"is_back_hook":0,"lexicon_symbols":null,"definition":"a funeral rite, also OBSEQUIE [n OBSEQUIES]"}