{"word":"BEFOOL","length":6,"playability":249.667,"playability_order":3076,"min_playability_order":3076,"max_playability_order":3076,"combinations0":5376,"probability_order0":13221,"min_probability_order0":13212,"max_probability_order0":13283,"combinations1":22784,"probability_order1":13826,"min_probability_order1":13823,"max_probability_order1":13851,"combinations2":28272,"probability_order2":13900,"min_probability_order2":13897,"max_probability_order2":13925,"alphagram":"BEFLOO","num_anagrams":1,"num_unique_letters":5,"num_vowels":3,"point_value":11,"front_hooks":null,"back_hooks":"s","is_front_hook":0,"is_back_hook":0,"lexicon_symbols":null,"definition":"to fool; to delude or lead into error [v -ED, -ING, -S]"}