{"word":"BELEED","length":6,"playability":156.75,"playability_order":6038,"min_playability_order":6038,"max_playability_order":6038,"combinations0":7040,"probability_order0":11583,"min_probability_order0":11583,"max_probability_order0":11598,"combinations1":25344,"probability_order1":13187,"min_probability_order1":13176,"max_probability_order1":13210,"combinations2":30040,"probability_order2":13534,"min_probability_order2":13534,"max_probability_order2":13549,"alphagram":"BDEEEL","num_anagrams":1,"num_unique_letters":4,"num_vowels":3,"point_value":9,"front_hooks":null,"back_hooks":null,"is_front_hook":0,"is_back_hook":1,"lexicon_symbols":null,"definition":"BELEE, (Shakespeare) to put on the lee side [v]"}