{"word":"HYPERPRODUCER","length":13,"playability":0.0,"playability_order":11235,"min_playability_order":125,"max_playability_order":14342,"combinations0":1351680,"probability_order0":13174,"min_probability_order0":13174,"max_probability_order0":13176,"combinations1":15022080,"probability_order1":13311,"min_probability_order1":13311,"max_probability_order1":13311,"combinations2":30374144,"probability_order2":13356,"min_probability_order2":13356,"max_probability_order2":13356,"alphagram":"CDEEHOPPRRRUY","num_anagrams":1,"num_unique_letters":9,"num_vowels":4,"point_value":26,"front_hooks":null,"back_hooks":"s","is_front_hook":0,"is_back_hook":0,"lexicon_symbols":null,"definition":"an agent causing hyperproduction [n -S]"}