{"word":"TALAKS","length":6,"playability":29.0,"playability_order":18221,"min_playability_order":18220,"max_playability_order":18240,"combinations0":3456,"probability_order0":15778,"min_probability_order0":15698,"max_probability_order0":16534,"combinations1":16704,"probability_order1":15775,"min_probability_order1":15772,"max_probability_order1":15790,"combinations2":21048,"probability_order2":16035,"min_probability_order2":16032,"max_probability_order2":16043,"alphagram":"AAKLST","num_anagrams":2,"num_unique_letters":5,"num_vowels":2,"point_value":10,"front_hooks":null,"back_hooks":null,"is_front_hook":0,"is_back_hook":1,"lexicon_symbols":null,"definition":"TALAK, (Arabic) in Islamic law, divorce, esp. by the husband's verbal repudiation of his wife in the presence of witnesses, also TALAQ [n]"}