{"word":"TRYING","length":6,"playability":72.8333,"playability_order":12225,"min_playability_order":12213,"max_playability_order":12225,"combinations0":11664,"probability_order0":8371,"min_probability_order0":8164,"max_probability_order0":8373,"combinations1":45360,"probability_order1":8324,"min_probability_order1":8321,"max_probability_order1":8325,"combinations2":54864,"probability_order2":8317,"min_probability_order2":8314,"max_probability_order2":8318,"alphagram":"GINRTY","num_anagrams":2,"num_unique_letters":6,"num_vowels":1,"point_value":10,"front_hooks":null,"back_hooks":"s","is_front_hook":0,"is_back_hook":0,"lexicon_symbols":null,"definition":"demanding, annoying [adj TRYINGLY] / the act of trying [n -S]"}