{"word":"ONE","length":3,"playability":26601.2,"playability_order":28,"min_playability_order":28,"max_playability_order":28,"combinations0":576,"probability_order0":17,"min_probability_order0":16,"max_probability_order0":21,"combinations1":1008,"probability_order1":17,"min_probability_order1":16,"max_probability_order1":21,"combinations2":1034,"probability_order2":17,"min_probability_order2":16,"max_probability_order2":21,"alphagram":"ENO","num_anagrams":2,"num_unique_letters":3,"num_vowels":2,"point_value":3,"front_hooks":"bcdfghlnprstz","back_hooks":"rs","is_front_hook":1,"is_back_hook":1,"lexicon_symbols":null,"definition":"an individual thing or person; the number or figure 1 [n -S]"}