{"word":"RADIALISES","length":10,"playability":1.0,"playability_order":6956,"min_playability_order":6272,"max_playability_order":13369,"combinations0":8957952,"probability_order0":4570,"min_probability_order0":4488,"max_probability_order0":4956,"combinations1":43296768,"probability_order1":5513,"min_probability_order1":5512,"max_probability_order1":5513,"combinations2":58475520,"probability_order2":5700,"min_probability_order2":5699,"max_probability_order2":5700,"alphagram":"AADEIILRSS","num_anagrams":1,"num_unique_letters":7,"num_vowels":5,"point_value":11,"front_hooks":null,"back_hooks":null,"is_front_hook":0,"is_back_hook":1,"lexicon_symbols":null,"definition":"RADIALISE, to arrange radially, also RADIALIZE [v]"}