{"word":"RASCHELS","length":8,"playability":17.7088,"playability_order":32691,"min_playability_order":32691,"max_playability_order":32691,"combinations0":62208,"probability_order0":27540,"min_probability_order0":27231,"max_probability_order0":28291,"combinations1":345600,"probability_order1":27916,"min_probability_order1":27858,"max_probability_order1":28089,"combinations2":484560,"probability_order2":27876,"min_probability_order2":27853,"max_probability_order2":27997,"alphagram":"ACEHLRSS","num_anagrams":2,"num_unique_letters":7,"num_vowels":2,"point_value":13,"front_hooks":null,"back_hooks":null,"is_front_hook":0,"is_back_hook":1,"lexicon_symbols":null,"definition":"RASCHEL, (German) a type of light loosely knitted cloth [n]"}