{"word":"EPHEBOPHILIAS","length":13,"playability":0.0,"playability_order":4306,"min_playability_order":125,"max_playability_order":14342,"combinations0":5474304,"probability_order0":11924,"min_probability_order0":11922,"max_probability_order0":11948,"combinations1":67530240,"probability_order1":11653,"min_probability_order1":11653,"max_probability_order1":11654,"combinations2":143384256,"probability_order2":11465,"min_probability_order2":11465,"max_probability_order2":11466,"alphagram":"ABEEHHIILOPPS","num_anagrams":1,"num_unique_letters":9,"num_vowels":6,"point_value":25,"front_hooks":null,"back_hooks":null,"is_front_hook":0,"is_back_hook":1,"lexicon_symbols":null,"definition":"EPHEBOPHILIA, sexual desire for youths or adolescents [n]"}