{"word":"CENTIMORGANS","length":12,"playability":0.0,"playability_order":8668,"min_playability_order":729,"max_playability_order":21016,"combinations0":201553920,"probability_order0":1335,"min_probability_order0":1321,"max_probability_order0":1369,"combinations1":1308980736,"probability_order1":1232,"min_probability_order1":1231,"max_probability_order1":1236,"combinations2":1988634240,"probability_order2":1177,"min_probability_order2":1176,"max_probability_order2":1181,"alphagram":"ACEGIMNNORST","num_anagrams":1,"num_unique_letters":11,"num_vowels":4,"point_value":17,"front_hooks":null,"back_hooks":null,"is_front_hook":0,"is_back_hook":1,"lexicon_symbols":null,"definition":"CENTIMORGAN, one hundredth of a morgan [n]"}