{"word":"NEUROHORMONE","length":12,"playability":0.0,"playability_order":19689,"min_playability_order":729,"max_playability_order":21016,"combinations0":13305600,"probability_order0":11807,"min_probability_order0":11802,"max_probability_order0":11807,"combinations1":86002560,"probability_order1":12578,"min_probability_order1":12577,"max_probability_order1":12578,"combinations2":131773536,"probability_order2":12972,"min_probability_order2":12971,"max_probability_order2":12972,"alphagram":"EEHMNNOOORRU","num_anagrams":1,"num_unique_letters":7,"num_vowels":6,"point_value":17,"front_hooks":null,"back_hooks":"s","is_front_hook":0,"is_back_hook":0,"lexicon_symbols":null,"definition":"a hormone (as acetylcholine or norepinephrine) produced by or acting on nervous tissue [n -S]"}