{"word":"ROSULAS","length":7,"playability":49.7559,"playability_order":20086,"min_playability_order":20086,"max_playability_order":20086,"combinations0":41472,"probability_order0":14380,"min_probability_order0":13751,"max_probability_order0":15013,"combinations1":171648,"probability_order1":15540,"min_probability_order1":15532,"max_probability_order1":15543,"combinations2":216672,"probability_order2":15577,"min_probability_order2":15569,"max_probability_order2":15580,"alphagram":"ALORSSU","num_anagrams":1,"num_unique_letters":6,"num_vowels":3,"point_value":7,"front_hooks":null,"back_hooks":null,"is_front_hook":0,"is_back_hook":1,"lexicon_symbols":null,"definition":"ROSULA, (Latin) a leaf-rosette [n]"}