{"word":"DESTITUTED","length":10,"playability":0.0,"playability_order":31907,"min_playability_order":13977,"max_playability_order":37196,"combinations0":1140480,"probability_order0":21907,"min_probability_order0":21757,"max_probability_order0":21973,"combinations1":6180480,"probability_order1":23684,"min_probability_order1":23684,"max_probability_order1":23687,"combinations2":8842704,"probability_order2":24307,"min_probability_order2":24307,"max_probability_order2":24310,"alphagram":"DDEEISTTTU","num_anagrams":1,"num_unique_letters":6,"num_vowels":4,"point_value":12,"front_hooks":null,"back_hooks":null,"is_front_hook":0,"is_back_hook":1,"lexicon_symbols":null,"definition":"DESTITUTE, to forsake, to deprive [v]"}