{"word":"PENSILE","length":7,"playability":212.393,"playability_order":2989,"min_playability_order":2989,"max_playability_order":2989,"combinations0":114048,"probability_order0":5567,"min_probability_order0":5284,"max_probability_order0":5601,"combinations1":446976,"probability_order1":5580,"min_probability_order1":5368,"max_probability_order1":5596,"combinations2":544632,"probability_order2":5588,"min_probability_order2":5376,"max_probability_order2":5604,"alphagram":"EEILNPS","num_anagrams":1,"num_unique_letters":6,"num_vowels":3,"point_value":9,"front_hooks":null,"back_hooks":null,"is_front_hook":1,"is_back_hook":1,"lexicon_symbols":null,"definition":"hanging loosely [adj]"}