{"word":"GARDENIAS","length":9,"playability":42.0,"playability_order":1015,"min_playability_order":1015,"max_playability_order":1023,"combinations0":6718464,"probability_order0":719,"min_probability_order0":706,"max_probability_order0":862,"combinations1":28366848,"probability_order1":810,"min_probability_order1":808,"max_probability_order1":826,"combinations2":36018432,"probability_order2":869,"min_probability_order2":867,"max_probability_order2":885,"alphagram":"AADEGINRS","num_anagrams":2,"num_unique_letters":8,"num_vowels":4,"point_value":11,"front_hooks":null,"back_hooks":null,"is_front_hook":0,"is_back_hook":1,"lexicon_symbols":null,"definition":"GARDENIA, a tropical shrub or tree with fragrant flowers of a waxy appearance [n]"}