{"word":"ALTERNANT","length":9,"playability":11.5,"playability_order":8999,"min_playability_order":8975,"max_playability_order":9119,"combinations0":2332800,"probability_order0":5140,"min_probability_order0":5139,"max_probability_order0":5161,"combinations1":9564480,"probability_order1":6877,"min_probability_order1":6876,"max_probability_order1":6880,"combinations2":12183048,"probability_order2":7278,"min_probability_order2":7277,"max_probability_order2":7281,"alphagram":"AAELNNRTT","num_anagrams":1,"num_unique_letters":6,"num_vowels":3,"point_value":9,"front_hooks":null,"back_hooks":"s","is_front_hook":0,"is_back_hook":0,"lexicon_symbols":null,"definition":"composed of alternate layers, as some rocks [adj] / a spelling or sound variant that does not affect meaning (allomorph or allophone) [n -S]"}