{"word":"BOURSIERS","length":9,"playability":9.0,"playability_order":11663,"min_playability_order":11335,"max_playability_order":11902,"combinations0":622080,"probability_order0":18398,"min_probability_order0":18172,"max_probability_order0":18570,"combinations1":3279744,"probability_order1":18876,"min_probability_order1":18836,"max_probability_order1":18914,"combinations2":4548096,"probability_order2":19078,"min_probability_order2":19056,"max_probability_order2":19094,"alphagram":"BEIORRSSU","num_anagrams":1,"num_unique_letters":7,"num_vowels":4,"point_value":11,"front_hooks":null,"back_hooks":null,"is_front_hook":0,"is_back_hook":1,"lexicon_symbols":null,"definition":"BOURSIER, (French) a foundation-scholar; a speculator on the Stock Exchange [n]"}