{"word":"CONVEYORS","length":9,"playability":9.2,"playability_order":11260,"min_playability_order":11250,"max_playability_order":11263,"combinations0":387072,"probability_order0":23083,"min_probability_order0":22984,"max_probability_order0":23153,"combinations1":2285568,"probability_order1":23253,"min_probability_order1":23240,"max_probability_order1":23267,"combinations2":3278208,"probability_order2":23263,"min_probability_order2":23250,"max_probability_order2":23277,"alphagram":"CENOORSVY","num_anagrams":1,"num_unique_letters":8,"num_vowels":3,"point_value":17,"front_hooks":null,"back_hooks":null,"is_front_hook":0,"is_back_hook":1,"lexicon_symbols":null,"definition":"CONVEYOR, one that conveys, also CONVEYER [n]"}