{"word":"EFS","length":3,"playability":6747.28,"playability_order":527,"min_playability_order":527,"max_playability_order":527,"combinations0":96,"probability_order0":540,"min_probability_order0":502,"max_probability_order0":612,"combinations1":256,"probability_order1":522,"min_probability_order1":502,"max_probability_order1":548,"combinations2":274,"probability_order2":519,"min_probability_order2":489,"max_probability_order2":548,"alphagram":"EFS","num_anagrams":2,"num_unique_letters":3,"num_vowels":1,"point_value":6,"front_hooks":"knrt","back_hooks":null,"is_front_hook":0,"is_back_hook":1,"lexicon_symbols":null,"definition":"EF, the letter F [n]"}