{"word":"CHOCKOS","length":7,"playability":4.0,"playability_order":33445,"min_playability_order":33405,"max_playability_order":33474,"combinations0":224,"probability_order0":33657,"min_probability_order0":33653,"max_probability_order0":33663,"combinations1":2032,"probability_order1":34024,"min_probability_order1":34021,"max_probability_order1":34028,"combinations2":3484,"probability_order2":34057,"min_probability_order2":34054,"max_probability_order2":34061,"alphagram":"CCHKOOS","num_anagrams":1,"num_unique_letters":5,"num_vowels":2,"point_value":18,"front_hooks":null,"back_hooks":null,"is_front_hook":0,"is_back_hook":1,"lexicon_symbols":null,"definition":"CHOCKO, (Australian slang) in World War II, a conscript, also CHOCO [n]"}