{"word":"VERSICLES","length":9,"playability":7.90909,"playability_order":13291,"min_playability_order":13291,"max_playability_order":13292,"combinations0":342144,"probability_order0":24721,"min_probability_order0":24464,"max_probability_order0":24822,"combinations1":1968192,"probability_order1":25159,"min_probability_order1":25054,"max_probability_order1":25194,"combinations2":2811600,"probability_order2":25322,"min_probability_order2":25224,"max_probability_order2":25354,"alphagram":"CEEILRSSV","num_anagrams":1,"num_unique_letters":7,"num_vowels":3,"point_value":14,"front_hooks":null,"back_hooks":null,"is_front_hook":0,"is_back_hook":1,"lexicon_symbols":null,"definition":"VERSICLE, a short verse in a church service normally followed by response [n]"}