{"word":"ANISOCERCAL","length":11,"playability":0.0,"playability_order":4295,"min_playability_order":2783,"max_playability_order":29010,"combinations0":17915904,"probability_order0":6975,"min_probability_order0":6946,"max_probability_order0":7274,"combinations1":139843584,"probability_order1":5664,"min_probability_order1":5663,"max_probability_order1":5676,"combinations2":223658496,"probability_order2":5120,"min_probability_order2":5119,"max_probability_order2":5126,"alphagram":"AACCEILNORS","num_anagrams":1,"num_unique_letters":9,"num_vowels":5,"point_value":15,"front_hooks":null,"back_hooks":null,"is_front_hook":0,"is_back_hook":0,"lexicon_symbols":null,"definition":"of fish, having unequal tail-lobes [adj]"}