{"word":"TOGED","length":5,"playability":637.372,"playability_order":2282,"min_playability_order":2282,"max_playability_order":2282,"combinations0":6912,"probability_order0":1166,"min_probability_order0":1095,"max_probability_order0":1295,"combinations1":20160,"probability_order1":1171,"min_probability_order1":1169,"max_probability_order1":1188,"combinations2":22560,"probability_order2":1171,"min_probability_order2":1169,"max_probability_order2":1188,"alphagram":"DEGOT","num_anagrams":2,"num_unique_letters":5,"num_vowels":2,"point_value":7,"front_hooks":null,"back_hooks":null,"is_front_hook":0,"is_back_hook":1,"lexicon_symbols":null,"definition":"(Shakespeare) clad in a toga [adj]"}