{"word":"CARAVANEERS","length":11,"playability":1.0,"playability_order":557,"min_playability_order":539,"max_playability_order":2726,"combinations0":7983360,"probability_order0":12334,"min_probability_order0":12334,"max_probability_order0":12358,"combinations1":46735488,"probability_order1":13294,"min_probability_order1":13294,"max_probability_order1":13298,"combinations2":67897440,"probability_order2":13770,"min_probability_order2":13770,"max_probability_order2":13774,"alphagram":"AAACEENRRSV","num_anagrams":1,"num_unique_letters":7,"num_vowels":5,"point_value":16,"front_hooks":null,"back_hooks":null,"is_front_hook":0,"is_back_hook":1,"lexicon_symbols":null,"definition":"CARAVANEER, the leader of a caravan, also CARAVANER, CARAVANNER [n]"}