{"word":"WHORE","length":5,"playability":344.775,"playability_order":4468,"min_playability_order":4468,"max_playability_order":4468,"combinations0":2304,"probability_order0":5142,"min_probability_order0":4852,"max_probability_order0":5313,"combinations1":8640,"probability_order1":4707,"min_probability_order1":4655,"max_probability_order1":4730,"combinations2":10184,"probability_order2":4543,"min_probability_order2":4494,"max_probability_order2":4566,"alphagram":"EHORW","num_anagrams":2,"num_unique_letters":5,"num_vowels":2,"point_value":11,"front_hooks":null,"back_hooks":"ds","is_front_hook":1,"is_back_hook":0,"lexicon_symbols":null,"definition":"to consort with prostitutes [v WHORED, WHORING, WHORES]"}