{"word":"OVERCLUB","length":8,"playability":53.6429,"playability_order":18288,"min_playability_order":18286,"max_playability_order":18289,"combinations0":73728,"probability_order0":26210,"min_probability_order0":26202,"max_probability_order0":26289,"combinations1":423936,"probability_order1":25918,"min_probability_order1":25913,"max_probability_order1":25961,"combinations2":597760,"probability_order2":25564,"min_probability_order2":25559,"max_probability_order2":25606,"alphagram":"BCELORUV","num_anagrams":1,"num_unique_letters":8,"num_vowels":3,"point_value":15,"front_hooks":null,"back_hooks":"s","is_front_hook":0,"is_back_hook":0,"lexicon_symbols":null,"definition":"to hit a shot too far through using a club with insufficient loft [v OVERCLUBBED, OVERCLUBBING, OVERCLUBS]"}