{"word":"SILKALENES","length":10,"playability":0.0,"playability_order":24278,"min_playability_order":13977,"max_playability_order":37196,"combinations0":1154736,"probability_order0":21752,"min_probability_order0":21743,"max_probability_order0":21756,"combinations1":7861536,"probability_order1":21456,"min_probability_order1":21455,"max_probability_order1":21456,"combinations2":11993184,"probability_order2":21425,"min_probability_order2":21424,"max_probability_order2":21425,"alphagram":"AEEIKLLNSS","num_anagrams":1,"num_unique_letters":7,"num_vowels":4,"point_value":14,"front_hooks":null,"back_hooks":null,"is_front_hook":0,"is_back_hook":1,"lexicon_symbols":null,"definition":"SILKALENE, a soft light cotton fabric resembling silk, also SILKALINE, SILKOLINE [n]"}