{"word":"PRAISERS","length":8,"playability":22.6626,"playability_order":30182,"min_playability_order":30182,"max_playability_order":30182,"combinations0":174960,"probability_order0":16631,"min_probability_order0":16553,"max_probability_order0":16680,"combinations1":830088,"probability_order1":17445,"min_probability_order1":17405,"max_probability_order1":17474,"combinations2":1100034,"probability_order2":17638,"min_probability_order2":17614,"max_probability_order2":17642,"alphagram":"AEIPRRSS","num_anagrams":2,"num_unique_letters":6,"num_vowels":3,"point_value":10,"front_hooks":"u","back_hooks":null,"is_front_hook":1,"is_back_hook":1,"lexicon_symbols":null,"definition":"PRAISER, one who praises [n]"}