{"word":"MIMICRY","length":7,"playability":17.1667,"playability_order":29700,"min_playability_order":29695,"max_playability_order":29704,"combinations0":864,"probability_order0":33204,"min_probability_order0":33132,"max_probability_order0":33250,"combinations1":6768,"probability_order1":33352,"min_probability_order1":33346,"max_probability_order1":33354,"combinations2":10716,"probability_order2":33372,"min_probability_order2":33366,"max_probability_order2":33374,"alphagram":"CIIMMRY","num_anagrams":1,"num_unique_letters":5,"num_vowels":2,"point_value":16,"front_hooks":null,"back_hooks":null,"is_front_hook":0,"is_back_hook":0,"lexicon_symbols":null,"definition":"an act of mimicking [n MIMICRIES]"}