{"word":"MUMPISH","length":7,"playability":3.0,"playability_order":33665,"min_playability_order":33600,"max_playability_order":33671,"combinations0":576,"probability_order0":33452,"min_probability_order0":33366,"max_probability_order0":33458,"combinations1":4736,"probability_order1":33633,"min_probability_order1":33612,"max_probability_order1":33633,"combinations2":7732,"probability_order2":33656,"min_probability_order2":33635,"max_probability_order2":33656,"alphagram":"HIMMPSU","num_anagrams":1,"num_unique_letters":6,"num_vowels":2,"point_value":16,"front_hooks":null,"back_hooks":null,"is_front_hook":0,"is_back_hook":0,"lexicon_symbols":null,"definition":"sulky [adj MUMPISHLY]"}