{"word":"VENTIFACTS","length":10,"playability":3.0,"playability_order":2164,"min_playability_order":1835,"max_playability_order":3031,"combinations0":2799360,"probability_order0":14050,"min_probability_order0":13961,"max_probability_order0":14268,"combinations1":17480448,"probability_order1":13725,"min_probability_order1":13714,"max_probability_order1":13738,"combinations2":25846992,"probability_order2":13494,"min_probability_order2":13486,"max_probability_order2":13504,"alphagram":"ACEFINSTTV","num_anagrams":1,"num_unique_letters":9,"num_vowels":3,"point_value":18,"front_hooks":null,"back_hooks":null,"is_front_hook":0,"is_back_hook":1,"lexicon_symbols":null,"definition":"VENTIFACT, a stone polished by windblown sand [n]"}