{"word":"DEMIURGUS","length":9,"playability":1.2,"playability_order":30898,"min_playability_order":30871,"max_playability_order":30903,"combinations0":373248,"probability_order0":24051,"min_probability_order0":23347,"max_probability_order0":24180,"combinations1":2135808,"probability_order1":24162,"min_probability_order1":24095,"max_probability_order1":24169,"combinations2":3055968,"probability_order2":24174,"min_probability_order2":24157,"max_probability_order2":24179,"alphagram":"DEGIMRSUU","num_anagrams":1,"num_unique_letters":8,"num_vowels":4,"point_value":13,"front_hooks":null,"back_hooks":null,"is_front_hook":0,"is_back_hook":0,"lexicon_symbols":null,"definition":"(Greek) an inferior god who created the world; a creative power or spirit, also DEMIURGE [n -ES]"}