{"word":"FUSEES","length":6,"playability":77.6112,"playability_order":11735,"min_playability_order":11735,"max_playability_order":11735,"combinations0":3168,"probability_order0":16679,"min_probability_order0":16606,"max_probability_order0":16731,"combinations1":13296,"probability_order1":17315,"min_probability_order1":17288,"max_probability_order1":17328,"combinations2":16668,"probability_order2":17513,"min_probability_order2":17486,"max_probability_order2":17526,"alphagram":"EEFSSU","num_anagrams":1,"num_unique_letters":4,"num_vowels":3,"point_value":9,"front_hooks":null,"back_hooks":null,"is_front_hook":0,"is_back_hook":1,"lexicon_symbols":null,"definition":"FUSEE, (French) a large-headed friction match, also FUZEE [n]"}