{"word":"TRELLISWORKS","length":12,"playability":0.0,"playability_order":20635,"min_playability_order":729,"max_playability_order":21016,"combinations0":5598720,"probability_order0":15099,"min_probability_order0":15000,"max_probability_order0":15101,"combinations1":47246976,"probability_order1":15017,"min_probability_order1":15015,"max_probability_order1":15018,"combinations2":81602640,"probability_order2":15033,"min_probability_order2":15033,"max_probability_order2":15034,"alphagram":"EIKLLORRSSTW","num_anagrams":1,"num_unique_letters":9,"num_vowels":3,"point_value":19,"front_hooks":null,"back_hooks":null,"is_front_hook":0,"is_back_hook":1,"lexicon_symbols":null,"definition":"TRELLISWORK, latticework [n]"}