{"word":"VAHANA","length":6,"playability":236.5,"playability_order":3346,"min_playability_order":3346,"max_playability_order":3348,"combinations0":2016,"probability_order0":18497,"min_probability_order0":18490,"max_probability_order0":18540,"combinations1":8448,"probability_order1":19307,"min_probability_order1":19303,"max_probability_order1":19341,"combinations2":10512,"probability_order2":19621,"min_probability_order2":19617,"max_probability_order2":19624,"alphagram":"AAAHNV","num_anagrams":1,"num_unique_letters":4,"num_vowels":3,"point_value":12,"front_hooks":null,"back_hooks":"s","is_front_hook":0,"is_back_hook":0,"lexicon_symbols":null,"definition":"(Sanskrit) a vehicle in Indian myth [n -S]"}