{"word":"AIRLINE","length":7,"playability":1032.26,"playability_order":26,"min_playability_order":26,"max_playability_order":26,"combinations0":559872,"probability_order0":144,"min_probability_order0":95,"max_probability_order0":177,"combinations1":1710720,"probability_order1":173,"min_probability_order1":161,"max_probability_order1":177,"combinations2":1966032,"probability_order2":172,"min_probability_order2":160,"max_probability_order2":176,"alphagram":"AEIILNR","num_anagrams":1,"num_unique_letters":6,"num_vowels":4,"point_value":7,"front_hooks":"h","back_hooks":"rs","is_front_hook":0,"is_back_hook":0,"lexicon_symbols":null,"definition":"an air transportation system [n -S]"}