{"word":"TRANSFORMATIONS","length":15,"playability":0.0,"playability_order":1798,"min_playability_order":7,"max_playability_order":5925,"combinations0":734832000,"probability_order0":2261,"min_probability_order0":2261,"max_probability_order0":2262,"combinations1":5898484800,"probability_order1":2385,"min_probability_order1":2385,"max_probability_order1":2385,"combinations2":10169336160,"probability_order2":2452,"min_probability_order2":2452,"max_probability_order2":2452,"alphagram":"AAFIMNNOORRSSTT","num_anagrams":1,"num_unique_letters":9,"num_vowels":5,"point_value":20,"front_hooks":null,"back_hooks":null,"is_front_hook":0,"is_back_hook":1,"lexicon_symbols":null,"definition":"TRANSFORMATION, an act, process, or instance of transforming or being transformed [n]"}