{"word":"SPENDINGS","length":9,"playability":13.6667,"playability_order":7490,"min_playability_order":7473,"max_playability_order":7498,"combinations0":233280,"probability_order0":28406,"min_probability_order0":28245,"max_probability_order0":28452,"combinations1":1327104,"probability_order1":29172,"min_probability_order1":29141,"max_probability_order1":29176,"combinations2":1900476,"probability_order2":29468,"min_probability_order2":29462,"max_probability_order2":29470,"alphagram":"DEGINNPSS","num_anagrams":1,"num_unique_letters":7,"num_vowels":2,"point_value":13,"front_hooks":null,"back_hooks":null,"is_front_hook":0,"is_back_hook":1,"lexicon_symbols":null,"definition":"SPENDING, the act of spending [n]"}