{"word":"STATIONED","length":9,"playability":13.2037,"playability_order":7718,"min_playability_order":7718,"max_playability_order":7718,"combinations0":11197440,"probability_order0":208,"min_probability_order0":202,"max_probability_order0":218,"combinations1":44727552,"probability_order1":200,"min_probability_order1":195,"max_probability_order1":208,"combinations2":56008800,"probability_order2":200,"min_probability_order2":195,"max_probability_order2":208,"alphagram":"ADEINOSTT","num_anagrams":2,"num_unique_letters":8,"num_vowels":4,"point_value":10,"front_hooks":null,"back_hooks":null,"is_front_hook":0,"is_back_hook":0,"lexicon_symbols":null,"definition":"STATION, to assign to a position [v]"}