{"word":"SYNONYMIZED","length":11,"playability":0.0,"playability_order":25313,"min_playability_order":2783,"max_playability_order":29010,"combinations0":414720,"probability_order0":25892,"min_probability_order0":25863,"max_probability_order0":25899,"combinations1":4329216,"probability_order1":25539,"min_probability_order1":25538,"max_probability_order1":25539,"combinations2":8235168,"probability_order2":25346,"min_probability_order2":25345,"max_probability_order2":25346,"alphagram":"DEIMNNOSYYZ","num_anagrams":1,"num_unique_letters":9,"num_vowels":3,"point_value":29,"front_hooks":null,"back_hooks":null,"is_front_hook":0,"is_back_hook":1,"lexicon_symbols":null,"definition":"SYNONYMIZE, to make synonymous, also SYNONYMISE [v]"}